hannah/__init__.py
hannah/exceptions.py
hannah/http/__init__.py
hannah/http/mappings.py
hannah/http/session.py
hannah/models.py
hannah/parsers.py
hannah/tests/__init__.py
hannah/tests/test_http.py
hannah/tests/test_swagger.py
hannah-0.0.10.dist-info/LICENSE.txt
hannah-0.0.10.dist-info/METADATA
hannah-0.0.10.dist-info/WHEEL
hannah-0.0.10.dist-info/RECORD
