Metadata-Version: 2.1
Name: hannah
Version: 0.0.10
Summary: 
Home-page: https://github.com/suganthsundar/hannah
License: MIT
Author: suganthsundar
Author-email: suganthsundar@gmail.com
Requires-Python: >=3.7,<4.0
Classifier: License :: OSI Approved :: MIT License
Classifier: Programming Language :: Python :: 3
Classifier: Programming Language :: Python :: 3.7
Classifier: Programming Language :: Python :: 3.8
Classifier: Programming Language :: Python :: 3.9
Classifier: Programming Language :: Python :: 3.10
Classifier: Programming Language :: Python :: 3.11
Requires-Dist: cached-property (>=1.5.2,<2.0.0)
Requires-Dist: httpx (>=0.23.0,<0.24.0)
Project-URL: Repository, https://github.com/suganthsundar/hannah
